dayabay_data_official/__init__.py
dayabay_data_official/__version__.py
dayabay_data_official/dataset.py
dayabay_data_official/data/hdf5/README.md
dayabay_data_official/data/hdf5/dataset_info.yaml
dayabay_data_official/data/hdf5/detector_iav_matrix.hdf5
dayabay_data_official/data/hdf5/detector_lsnl_curves.hdf5
dayabay_data_official/data/hdf5/neutrino_rate.hdf5
dayabay_data_official/data/hdf5/nonequilibrium_correction.hdf5
dayabay_data_official/data/hdf5/reactor_antineutrino_spectra_hm.hdf5
dayabay_data_official/data/hdf5/reactor_antineutrino_spectra_hm_uncertainties.hdf5
dayabay_data_official/data/hdf5/snf_correction.hdf5
dayabay_data_official/data/hdf5/dayabay_dataset/dayabay_background_rates.hdf5
dayabay_data_official/data/hdf5/dayabay_dataset/dayabay_background_spectra_6AD.hdf5
dayabay_data_official/data/hdf5/dayabay_dataset/dayabay_background_spectra_7AD.hdf5
dayabay_data_official/data/hdf5/dayabay_dataset/dayabay_background_spectra_8AD.hdf5
dayabay_data_official/data/hdf5/dayabay_dataset/dayabay_daily_detector_data.hdf5
dayabay_data_official/data/hdf5/dayabay_dataset/dayabay_ibd_spectra_6AD.hdf5
dayabay_data_official/data/hdf5/dayabay_dataset/dayabay_ibd_spectra_7AD.hdf5
dayabay_data_official/data/hdf5/dayabay_dataset/dayabay_ibd_spectra_8AD.hdf5
dayabay_data_official/data/hdf5/parameters/antineutrinos_per_fission_huber_mueller.yaml
dayabay_data_official/data/hdf5/parameters/background_rate_scale_accidentals.yaml
dayabay_data_official/data/hdf5/parameters/background_rate_uncertainty_scale_amc.yaml
dayabay_data_official/data/hdf5/parameters/background_rate_uncertainty_scale_site.yaml
dayabay_data_official/data/hdf5/parameters/background_rates_correlated.yaml
dayabay_data_official/data/hdf5/parameters/background_rates_uncorrelated.yaml
dayabay_data_official/data/hdf5/parameters/baselines.yaml
dayabay_data_official/data/hdf5/parameters/conversion_survival_probability_argument.py
dayabay_data_official/data/hdf5/parameters/conversion_thermal_power.py
dayabay_data_official-1.0.1.dist-info/licenses/LICENSE
dayabay_data_official-1.0.1.dist-info/METADATA
dayabay_data_official-1.0.1.dist-info/WHEEL
dayabay_data_official-1.0.1.dist-info/top_level.txt
dayabay_data_official-1.0.1.dist-info/RECORD
