Metadata-Version: 2.4
Name: dayabay-data-official
Version: 1.0.1
Summary: Full Data Release of the Daya Bay Reactor Neutrino Experiment. Analysis dataset.
Author-email: Daya Bay Reactor Neutrino Experiment <yuzy@ihep.ac.cn>, Maxim Gonchar <gonchar@jinr.ru>, Zeyuan Yu <yuzy@ihep.ac.cn>, Vitalii Zavadskyi <zavadskyi@jinr.ru>
Maintainer-email: Daya Bay Reactor Neutrino Experiment <yuzy@ihep.ac.cn>, Maxim Gonchar <gonchar@jinr.ru>, Zeyuan Yu <yuzy@ihep.ac.cn>, Vitalii Zavadskyi <zavadskyi@jinr.ru>
Project-URL: Bug Reports, https://github.com/dayabay-experiment/dayabay-data-official/issues
Project-URL: Data, https://doi.org/10.5281/zenodo.17587229
Project-URL: Homepage, https://github.com/dayabay-experiment/dayabay-data-official
Project-URL: Repository, https://github.com/dayabay-experiment/dayabay-data-official
Keywords: data,dataset,dayabay-experiment,inverse-beta-decay,neutrino-mixing,neutrino-oscillation,reactor-neutrino
Classifier: Programming Language :: Python :: 3 :: Only
Classifier: Programming Language :: Python :: 3.10
Classifier: Programming Language :: Python :: 3.11
Classifier: Programming Language :: Python :: 3.12
Classifier: Programming Language :: Python :: 3.13
Classifier: Programming Language :: Python :: 3.14
License-File: LICENSE
Dynamic: license-file
